license_selector/__init__.py
license_selector/licence.py
license_selector-0.1.2.dist-info/LICENSE
license_selector-0.1.2.dist-info/METADATA
license_selector-0.1.2.dist-info/WHEEL
license_selector-0.1.2.dist-info/entry_points.txt
license_selector-0.1.2.dist-info/top_level.txt
license_selector-0.1.2.dist-info/RECORD
